django_laravel_validator-1.0.0.dist-info/DESCRIPTION.rst
django_laravel_validator-1.0.0.dist-info/METADATA
django_laravel_validator-1.0.0.dist-info/RECORD
django_laravel_validator-1.0.0.dist-info/WHEEL
django_laravel_validator-1.0.0.dist-info/entry_points.txt
django_laravel_validator-1.0.0.dist-info/metadata.json
django_laravel_validator-1.0.0.dist-info/top_level.txt
validator/__init__.py
validator/exceptions.py
validator/test.py
validator/validator.py
