Metadata-Version: 2.0
Name: django-laravel-validator
Version: 1.0.0
Summary: A laravel validator like django-use validator
Home-page: https://github.com/universalyouth/django-validator
Author: Younger Shen
Author-email: younger.x.shen@gmail.com
License: MIT
Keywords: django validator django-validator
Platform: UNKNOWN
Classifier: Development Status :: 4 - Beta
Classifier: Intended Audience :: Developers
Classifier: Topic :: Software Development :: Libraries :: Application Frameworks
Classifier: Framework :: Django :: 1.9
Classifier: License :: OSI Approved :: MIT License
Classifier: Programming Language :: Python :: 3.6
Requires-Dist: django
Provides-Extra: test
Requires-Dist: coverage; extra == 'test'
